sta_awscli/__init__.py
sta_awscli/sta_awscli.py
sta_awscli-2.1.4.dist-info/entry_points.txt
sta_awscli-2.1.4.dist-info/LICENSE
sta_awscli-2.1.4.dist-info/WHEEL
sta_awscli-2.1.4.dist-info/METADATA
sta_awscli-2.1.4.dist-info/RECORD
