Metadata-Version: 2.1
Name: sta-awscli
Version: 2.1.4
Summary: MFA for AWS CLI using SafeNet Trusted Access (STA)
Home-page: https://github.com/thalesdemo/sta-awscli
License: MIT
Author: Gur Talmor, Cina Shaykhian and Alex Basin
Requires-Python: >=3.8,<4.0
Classifier: License :: OSI Approved :: MIT License
Classifier: Operating System :: OS Independent
Classifier: Programming Language :: Python :: 3
Classifier: Programming Language :: Python :: 3.10
Classifier: Programming Language :: Python :: 3.8
Classifier: Programming Language :: Python :: 3.9
Requires-Dist: argcomplete (==2.0.0)
Requires-Dist: beautifulsoup4 (==4.11.1)
Requires-Dist: boto3 (==1.24.59)
Requires-Dist: botocore (==1.27.59)
Requires-Dist: bs4 (==0.0.1)
Requires-Dist: certifi (==2022.6.15)
Requires-Dist: charset-normalizer (==2.1.1)
Requires-Dist: colorama (==0.4.5)
Requires-Dist: decorator (==5.1.1)
Requires-Dist: fido2 (==1.0.0)
Requires-Dist: idna (==3.3)
Requires-Dist: jmespath (==1.0.1)
Requires-Dist: maskpass (==0.3.6)
Requires-Dist: numpy (==1.23.2)
Requires-Dist: opencv-python (==4.6.0.66)
Requires-Dist: packaging (==21.3)
Requires-Dist: pillow (==9.2.0)
Requires-Dist: pyparsing (==3.0.9)
Requires-Dist: pyreadline3 (==3.4.1)
Requires-Dist: pytesseract (==0.3.10)
Requires-Dist: python-dateutil (==2.8.2)
Requires-Dist: requests (==2.28.1)
Requires-Dist: s3transfer (==0.6.0)
Requires-Dist: scikit-build (==0.15.0)
Requires-Dist: six (==1.16.0)
Requires-Dist: soupsieve (==2.3.2.post1)
Requires-Dist: testresources (==2.0.1)
Requires-Dist: urllib3 (==1.26.12)
Requires-Dist: validators (==0.20.0)
Requires-Dist: wget (==3.2)
Requires-Dist: xmltodict (==0.13.0)
Project-URL: Repository, https://github.com/thalesdemo/sta-awscli
